LICENSE
MANIFEST.in
README.md
setup.py
colout2/__init__.py
colout2/__main__.py
colout2/colout.py
colout2/colout_autogen.py
colout2/colout_clang.py
colout2/colout_cmake.py
colout2/colout_configure.py
colout2/colout_ctest.py
colout2/colout_g++.py
colout2/colout_javac.py
colout2/colout_json.py
colout2/colout_latex.py
colout2/colout_ninja.py
colout2/colout_perm.py
colout2/colout_python.py
colout2/colout_valgrind.py
colout2.egg-info/PKG-INFO
colout2.egg-info/SOURCES.txt
colout2.egg-info/dependency_links.txt
colout2.egg-info/entry_points.txt
colout2.egg-info/not-zip-safe
colout2.egg-info/requires.txt
colout2.egg-info/top_level.txt