Metadata-Version: 1.0
Name: colout2
Version: 1.0.1
Summary: Color Up Arbitrary Command Output.
Home-page: http://nojhan.github.com/colout/
Author: Omer Katz
Author-email: omer.drow@gmail.com
License:                     GNU GENERAL PUBLIC LICENSE
